loveyu
