Metadata-Version: 2.1
Name: loveyu
Version: 13.1.4
Summary: little tips to celebrate something
Home-page: UNKNOWN
Author: cpak00
Author-email: cymcpak00@gmail.com
License: GPLv2 Licence
Keywords: tips,image,celebrate
Platform: any
